agenthub/openai/__init__.py
agenthub/openai/core.py
agenthub/openai/types.py
agenthub/openai/util.py
agenthub/openai/repl/__init__.py
agenthub/openai/repl/repl.py
agenthub_openai-0.0.7.dist-info/METADATA
agenthub_openai-0.0.7.dist-info/WHEEL
agenthub_openai-0.0.7.dist-info/top_level.txt
agenthub_openai-0.0.7.dist-info/RECORD
