Metadata-Version: 2.1
Name: agenthub-openai
Version: 0.0.7
Summary: AgentHub openai package
Author-email: Jacob Weiss <jaweiss2305@gmail.com>
Project-URL: homepage, https://github.com/jacobweiss2305/agenthub
Project-URL: repository, https://github.com/jacobweiss2305/agenthub/tree/main/packages/openai
Requires-Python: >=3.7
Requires-Dist: agenthub-core
Requires-Dist: openai
